{
  "data": [
    {
      "id": 1,
      "title": "Al-Quran",
      "route" : "agama/al-quran",
      "description": "",
      "icon": ""
    },
    {
      "id": 3,
      "title": "Cuaca",
      "route" : "cuaca",
      "description": "",
      "icon": ""
    },
    {
      "id": 3,
      "title": "Shorten Link",
      "route" : "shorten",
      "description": "",
      "icon": ""
    },
    {
      "id": 4,
      "title": "Cek Ongkir",
      "route" : "cekongkir",
      "description": "",
      "icon": ""
    }
  ]
}
